iamusmanbro/__main__.py
iamusmanbro-0.0.6.dist-info/METADATA
iamusmanbro-0.0.6.dist-info/WHEEL
iamusmanbro-0.0.6.dist-info/top_level.txt
iamusmanbro-0.0.6.dist-info/RECORD
