Metadata-Version: 2.4
Name: iamusmanbro
Version: 0.0.6
Summary: Animated CLI intro and alias to usman-ghani
Author-email: Usman Ghani <iamusmanbro@gmail.com>
Keywords: iamusmanbro,usman-ghani,machine-learning,portfolio,automation,cli
Classifier: Programming Language :: Python :: 3
Classifier: Operating System :: OS Independent
Classifier: Environment :: Console
Classifier: Intended Audience :: Developers
Classifier: License :: OSI Approved :: MIT License
Requires-Python: >=3.7
Requires-Dist: usman-ghani
Requires-Dist: rich
